{
    "$schema": "http://json-schema.org/draft-07/schema#",
    "type": "object",
    "description": "Contains configuration of the component wrt to the cli project that determines the execution of cli commands.",
    "properties": {
        "component": {
            "description": "Name of the component in the gdk cli project. As of now, gdk supports only one component per project.",
            "type": "object",
            "maxProperties": 1,
            "minProperties": 1,
            "patternProperties": {
                "[a-zA-Z0-9-_.]+": {
                    "type": "object",
                    "properties": {
                        "author": {
                            "description": "Author of the component which is interpolated during build and publish phases.",
                            "type": "string"
                        },
                        "version": {
                            "description": "Version of the component which is interpolated during build and publish phases. Can be an enum or a semver version.",
                            "type": "string",
                            "oneOf": [
                                {
                                    "description": "Exact version of the component to use with cli commands. Must be a semver version.",
                                    "pattern": "^(0|[1-9]\\d*)\\.(0|[1-9]\\d*)\\.(0|[1-9]\\d*)(?:-((?:0|[1-9]\\d*|\\d*[a-zA-Z-][0-9a-zA-Z-]*)(?:\\.(?:0|[1-9]\\d*|\\d*[a-zA-Z-][0-9a-zA-Z-]*))*))?(?:\\+([0-9a-zA-Z-]+(?:\\.[0-9a-zA-Z-]+)*))?"
                                },
                                {
                                    "description": "Enum to dynamically determine the version of the component with cli commands.",
                                    "enum": [
                                        "NEXT_PATCH"
                                    ]
                                }
                            ]
                        },
                        "build": {
                            "type": "object",
                            "description": "Configuration used with the build command of the cli.",
                            "properties": {
                                "custom_build_command": {
                                    "description": "Custom command provided as an array of strings to execute with cli build command. Required when the 'build_system' is 'custom'.",
                                    "type": [
                                        "array",
                                        "string"
                                    ],
                                    "minItems": 1,
                                    "minLength": 1
                                },
                                "build_system": {
                                    "description": "Build system to use with the cli build command. Must be one of the defaults supported by the cli or just 'custom'.",
                                    "type": "string",
                                    "enum": [
                                        "zip",
                                        "maven",
                                        "gradle",
                                        "gradlew",
                                        "custom"
                                    ]
                                }
                            },
                            "required": [
                                "build_system"
                            ],
                            "dependentRequired": {
                                "custom_build_command": [
                                    "build_system"
                                ]
                            },
                            "allOf": [
                                {
                                    "if": {
                                        "properties": {
                                            "build_system": {
                                                "const": "zip"
                                            }
                                        }
                                    },
                                    "then": {
                                        "properties": {
                                            "options": {
                                                "type": "object",
                                                "description": "configuration options for the zip build system",
                                                "properties": {
                                                    "excludes": {
                                                        "type": "array",
                                                        "description": "regex patterns of files to exclude",
                                                        "minItems": 1
                                                    }
                                                },
                                                "additionalProperties": false
                                            }
                                        }
                                    }
                                },
                                {
                                    "if": {
                                        "properties": {
                                            "build_system": {
                                                "const": "custom"
                                            }
                                        }
                                    },
                                    "then": {
                                        "properties": {
                                            "custom_build_command": {}
                                        },
                                        "required": [
                                            "custom_build_command"
                                        ]
                                    }
                                }
                            ]
                        },
                        "publish": {
                            "type": "object",
                            "description": "Configuration used with the publish command of the cli.",
                            "properties": {
                                "bucket": {
                                    "description": "Prefix of the s3 bucket used during component artifacts upload. Name of the bucket is created by appending account and region to bucket prefix.",
                                    "type": "string"
                                },
                                "region": {
                                    "description": "AWS regions supported by AWS IoT Greengrassv2. Must be one of the enum values.",
                                    "type": "string",
                                    "enum": [
                                        "us-east-2",
                                        "us-east-1",
                                        "us-west-2",
                                        "ap-south-1",
                                        "ap-northeast-2",
                                        "ap-southeast-1",
                                        "ap-southeast-2",
                                        "ap-northeast-1",
                                        "ca-central-1",
                                        "cn-north-1",
                                        "eu-central-1",
                                        "eu-west-1",
                                        "eu-west-2",
                                        "us-gov-west-1",
                                        "us-gov-east-1"
                                    ]
                                },
                                "options": {
                                    "type": "object",
                                    "description": "configuration options used during component version creation",
                                    "properties": {
                                        "file_upload_args": {
                                            "type": "object",
                                            "description": "Extra arguments used by S3 client during file transfer."
                                        }
                                    }
                                }
                            },
                            "required": [
                                "bucket",
                                "region"
                            ]
                        }
                    },
                    "required": [
                        "author",
                        "version",
                        "build",
                        "publish"
                    ]
                }
            }
        },
        "gdk_version": {
            "description": "Version of the gdk cli tool compatible with the provided configuration.",
            "type": "string",
            "pattern": "^(0|[1-9]\\d*)\\.(0|[1-9]\\d*)\\.(0|[1-9]\\d*)(?:-((?:0|[1-9]\\d*|\\d*[a-zA-Z-][0-9a-zA-Z-]*)(?:\\.(?:0|[1-9]\\d*|\\d*[a-zA-Z-][0-9a-zA-Z-]*))*))?(?:\\+([0-9a-zA-Z-]+(?:\\.[0-9a-zA-Z-]+)*))?"
        }
    },
    "required": [
        "component",
        "gdk_version"
    ]
}
